LICENSE
README.md
setup.py
xyzflow/EvaluatedValue.py
xyzflow/Flow.py
xyzflow/HelperTasks.py
xyzflow/Parameter.py
xyzflow/Task.py
xyzflow/__init__.py
xyzflow/xyzflow.py
xyzflow.egg-info/PKG-INFO
xyzflow.egg-info/SOURCES.txt
xyzflow.egg-info/dependency_links.txt
xyzflow.egg-info/entry_points.txt
xyzflow.egg-info/not-zip-safe
xyzflow.egg-info/requires.txt
xyzflow.egg-info/top_level.txt