Metadata-Version: 2.1
Name: xyzflow
Version: 0.1
Summary: Simple but powerful python orchestration framework
Home-page: https://github.com/Renneke/xyzflow
Author: Florian Renneke
Author-email: florianrenneke@gmail.com
License: Apache License Version 2.0
Platform: UNKNOWN
License-File: LICENSE
